GptModule/__init__.py
GptModule/struct.py
Gptmodule-0.1.0.dist-info/METADATA
Gptmodule-0.1.0.dist-info/WHEEL
Gptmodule-0.1.0.dist-info/top_level.txt
Gptmodule-0.1.0.dist-info/RECORD
